videodrome/__init__.py
videodrome/__main__.py
videodrome/generate.py
videodrome/themes/default/static/css/main.css
videodrome/themes/default/static/css/videoplayer.css
videodrome/themes/default/static/images/background.png
videodrome/themes/default/static/images/poster_film.png
videodrome/themes/default/static/images/poster_folder.png
videodrome/themes/default/static/images/poster_video.png
videodrome/themes/default/static/js/jquery/jquery-3.2.1.min.js
videodrome/themes/default/static/js/keynav/keynav.js
videodrome/themes/default/static/js/videoplayer/videoplayer.js
videodrome/themes/default/static/sounds/back.wav
videodrome/themes/default/static/sounds/click.wav
videodrome/themes/default/static/sounds/hover.wav
videodrome/themes/default/templates/index.html
videodrome/themes/default/templates/videoplayer.html
videodrome-0.2.4.dist-info/METADATA
videodrome-0.2.4.dist-info/RECORD
videodrome-0.2.4.dist-info/WHEEL
videodrome-0.2.4.dist-info/entry_points.txt
videodrome-0.2.4.dist-info/top_level.txt
