Metadata-Version: 2.1
Name: videodrome
Version: 0.2.4
Summary: Static Media Center Generator in Python with HTML5 UI
Home-page: https://github.com/p5yb14d3/videodrome
Author: p5yb14d3
Author-email: p5yb14d3@gmail.com
License: MIT
Platform: UNKNOWN
Classifier: Programming Language :: Python :: 2.7
Classifier: License :: OSI Approved :: MIT License
Classifier: Operating System :: OS Independent
Requires-Dist: jinja2 (==2.10)
